jammy/__init__.py
jammy/cli/__init__.py
jammy/cli/argument.py
jammy/cli/cmd_utils.py
jammy/cli/cmdline_viz.py
jammy/cli/colors.py
jammy/cli/device.py
jammy/cli/keyboard.py
jammy/cli_scripts/__init__.py
jammy/cli_scripts/dk.py
jammy/cli_scripts/gpu_sc.py
jammy/cli_scripts/inspect_file.py
jammy/cli_scripts/shell_executor.py
jammy/cli_scripts/sort_yaml.py
jammy/cli_scripts/sys_info.py
jammy/cli_scripts/conf/__init__.py
jammy/cli_scripts/conf/jamdk.yaml
jammy/collections/__init__.py
jammy/collections/lazy_dict.py
jammy/comm/__init__.py
jammy/comm/cs.py
jammy/comm/utils.py
jammy/concurrency/__init__.py
jammy/concurrency/packing.py
jammy/concurrency/zmq_utils.py
jammy/event/__init__.py
jammy/event/registry.py
jammy/fileio/README.md
jammy/fileio/__init__.py
jammy/fileio/file_client.py
jammy/fileio/io.py
jammy/fileio/parse.py
jammy/fileio/backends/__init__.py
jammy/fileio/backends/base.py
jammy/fileio/backends/boto3_backend.py
jammy/fileio/backends/boto3_client.py
jammy/fileio/backends/http_backend.py
jammy/fileio/backends/lmdb_backend.py
jammy/fileio/backends/local_backend.py
jammy/fileio/backends/memcached_backend.py
jammy/fileio/backends/registry_utils.py
jammy/fileio/handlers/__init__.py
jammy/fileio/handlers/base.py
jammy/fileio/handlers/imageio_video_handler.py
jammy/fileio/handlers/json_handler.py
jammy/fileio/handlers/np_handler.py
jammy/fileio/handlers/pickle_handler.py
jammy/fileio/handlers/pil_handler.py
jammy/fileio/handlers/registry_utils.py
jammy/fileio/handlers/tarfile_handler.py
jammy/fileio/handlers/torch_handler.py
jammy/fileio/handlers/torchjit_handler.py
jammy/fileio/handlers/yaml_handler.py
jammy/image/__init__.py
jammy/image/backend.py
jammy/image/codecs.py
jammy/image/imgio.py
jammy/image/imgproc.py
jammy/io/__init__.py
jammy/io/common.py
jammy/io/fs.py
jammy/io/path.py
jammy/io/tempfile.py
jammy/logging/__init__.py
jammy/logging/fake_logger.py
jammy/logging/logger.py
jammy/logging/wandb_utils.py
jammy/random/__init__.py
jammy/random/_lazy_bind.py
jammy-0.1.48.dist-info/METADATA
jammy-0.1.48.dist-info/WHEEL
jammy-0.1.48.dist-info/entry_points.txt
jammy-0.1.48.dist-info/RECORD
