Metadata-Version: 2.4
Name: jammy
Version: 0.1.48
Summary: A Versatile ToolBox
Project-URL: Documentation, https://jammy.readthedocs.io/en/latest/
Author-email: Qin <qsh.zh27@gmail.com>
License: MIT
Requires-Python: >=3.8.1
Requires-Dist: einops>=0.6.0
Requires-Dist: filelock>=3.8.0
Requires-Dist: gitpython>=3.1.17
Requires-Dist: gpustat>=0.6.0
Requires-Dist: hydra-core>=1.2.1
Requires-Dist: ipdb>=0.13.8
Requires-Dist: loguru>=0.7.0
Requires-Dist: matplotlib>=3.7.1
Requires-Dist: numpy>=1.24.1
Requires-Dist: pandas>=1.3.0
Requires-Dist: scipy>=1.10.1
Requires-Dist: stackprinter>=0.2.10
Requires-Dist: timeout-decorator>=0.5.0
Requires-Dist: tqdm>=4.11.0
Provides-Extra: all
Requires-Dist: h5py>=3.4.0; extra == 'all'
Requires-Dist: lightning>=2.0.0; extra == 'all'
Requires-Dist: line-profiler>=3.3.1; extra == 'all'
Requires-Dist: lmdb>=1.2.1; extra == 'all'
Requires-Dist: msgpack-numpy>=0.4.7; extra == 'all'
Requires-Dist: msgpack>=1.0.2; extra == 'all'
Requires-Dist: pandas>=1.3.0; extra == 'all'
Requires-Dist: parse>=1.19.0; extra == 'all'
Requires-Dist: plotly>=5.20.0; extra == 'all'
Requires-Dist: pudb>=2022.1; extra == 'all'
Requires-Dist: pyarrow>=6.0.0; extra == 'all'
Requires-Dist: python-memcached>=1.59; extra == 'all'
Requires-Dist: pyzmq>=22.3.0; extra == 'all'
Requires-Dist: torch>=2.0.0; extra == 'all'
Requires-Dist: torchinfo>=1.5.3; extra == 'all'
Requires-Dist: torchvision>=0.15.0; extra == 'all'
Requires-Dist: tornado>=6.1; extra == 'all'
Requires-Dist: ubelt>=0.10.2; extra == 'all'
Requires-Dist: wandb>=0.10.31; extra == 'all'
Provides-Extra: dev
Requires-Dist: black>=21.5b1; extra == 'dev'
Requires-Dist: isort>=5.8.0; extra == 'dev'
Requires-Dist: m2r2>=0.3.1; extra == 'dev'
Requires-Dist: pallets-sphinx-themes>=2.0.1; extra == 'dev'
Requires-Dist: pre-commit>=2.13.0; extra == 'dev'
Requires-Dist: pylint>=2.8.3; extra == 'dev'
Requires-Dist: pytest>=7.4.3; extra == 'dev'
Requires-Dist: sphinx-tabs>=3.2.0; extra == 'dev'
Requires-Dist: sphinx>=4.2.0; extra == 'dev'
Provides-Extra: learn
Requires-Dist: wandb>=0.10.31; extra == 'learn'
Provides-Extra: pro
Requires-Dist: line-profiler>=3.3.1; extra == 'pro'
Requires-Dist: parse>=1.19.0; extra == 'pro'
Requires-Dist: pudb>=2022.1; extra == 'pro'
Requires-Dist: ubelt>=0.10.2; extra == 'pro'
Provides-Extra: storage
Requires-Dist: h5py>=3.4.0; extra == 'storage'
Requires-Dist: lmdb>=1.2.1; extra == 'storage'
Requires-Dist: msgpack-numpy>=0.4.7; extra == 'storage'
Requires-Dist: msgpack>=1.0.2; extra == 'storage'
Requires-Dist: pyarrow>=6.0.0; extra == 'storage'
Requires-Dist: python-memcached>=1.59; extra == 'storage'
Provides-Extra: torch
Requires-Dist: lightning>=2.0.0; extra == 'torch'
Requires-Dist: torch>=2.0.0; extra == 'torch'
Requires-Dist: torchinfo>=1.5.3; extra == 'torch'
Requires-Dist: torchvision>=0.15.0; extra == 'torch'
Requires-Dist: wandb>=0.10.31; extra == 'torch'
Provides-Extra: viz
Requires-Dist: plotly>=5.20.0; extra == 'viz'
Provides-Extra: web
Requires-Dist: pyzmq>=22.3.0; extra == 'web'
Requires-Dist: tornado>=6.1; extra == 'web'
